sandbox/__init__.py
sandbox/main.py
test/__init__.py
test/testlib.py
test/test_exec/__init__.py
test/test_exec/plugin.py
test/test_exec/test_exec.py
test/test_open/__init__.py
test/test_open/plugin.py
test/test_open/test_open.py
test/test_print/__init__.py
test/test_print/plugin.py
test/test_print/test_print.py
test/test_sys/__init__.py
test/test_sys/plugin.py
test/test_sys/test_sys.py
lite_sandbox-0.0.2.dist-info/LICENSE
lite_sandbox-0.0.2.dist-info/METADATA
lite_sandbox-0.0.2.dist-info/WHEEL
lite_sandbox-0.0.2.dist-info/top_level.txt
lite_sandbox-0.0.2.dist-info/RECORD
